foo/__init__.py
gs_lib.libs/libarrow-aadd8168.so.100.1.0
gs_lib.libs/libvineyard_io-d74d0e87.so
gs_lib.libs/libvineyard_client-86d04c92.so
gs_lib.libs/libgrpc++_reflection-5e87883f.so.1.33.1
gs_lib.libs/libabsl_stacktrace-cb0e4ad0.so
gs_lib.libs/libabsl_civil_time-2bcb31a7.so
gs_lib.libs/libabsl_throw_delegate-f4c943d5.so
gs_lib.libs/libabsl_bad_variant_access-864444a8.so
gs_lib.libs/libunwind-d5b5a318.so.8.0.1
gs_lib.libs/libmpi-a28fc733.so.40.20.5
gs_lib.libs/libgflags-bfe586c4.so.2.2.2
gs_lib.libs/libboost_system-6c8f677a.so.1.73.0
gs_lib.libs/libssl-84bdb2df.so.1.1
gs_lib.libs/libgrpc++-270af443.so.1.33.1
gs_lib.libs/libabsl_symbolize-efd3cf23.so
gs_lib.libs/libunwind-x86_64-b0951408.so.8.0.1
gs_lib.libs/libabsl_base-bfc48bb1.so
gs_lib.libs/libvineyard_basic-7e0f1c29.so
gs_lib.libs/libvineyard_malloc-264ab80a.so
gs_lib.libs/libmpi_cxx-6cc9d6b2.so.40.20.1
gs_lib.libs/libgrpc-bf4f9c3b.so.13.0.0
gs_lib.libs/libgpr-e2f58653.so.13.0.0
gs_lib.libs/libabsl_raw_logging_internal-3d442703.so
gs_lib.libs/libabsl_time-d1155ff5.so
gs_lib.libs/libabsl_status-cb9b117c.so
gs_lib.libs/libabsl_str_format_internal-55b05e9c.so
gs_lib.libs/libgomp-a34b3233.so.1.0.0
gs_lib.libs/libabsl_debugging_internal-f4d16b52.so
gs_lib.libs/libabsl_malloc_internal-c6176dbd.so
gs_lib.libs/libabsl_strings-acd91500.so
gs_lib.libs/libabsl_demangle_internal-9232dc90.so
gs_lib.libs/libcrypto-df6de5ba.so.1.1
gs_lib.libs/libboost_context-8ad90b65.so.1.73.0
gs_lib.libs/libabsl_raw_hash_set-34f38283.so
gs_lib.libs/libglog-faa49ff8.so.0.4.0
gs_lib.libs/libabsl_spinlock_wait-ec322322.so
gs_lib.libs/libabsl_time_zone-0d40316e.so
gs_lib.libs/libabsl_hashtablez_sampler-9d6b82b9.so
gs_lib.libs/libboost_filesystem-9f76979b.so.1.73.0
gs_lib.libs/libabsl_log_severity-d98d251a.so
gs_lib.libs/libabsl_dynamic_annotations-4b05d809.so
gs_lib.libs/libabsl_synchronization-f5236a92.so
gs_lib.libs/libabsl_exponential_biased-fd91b7e5.so
gs_lib-0.13.0.dist-info/WHEEL
gs_lib-0.13.0.dist-info/top_level.txt
gs_lib-0.13.0.dist-info/METADATA
gs_lib-0.13.0.dist-info/RECORD
